PyCUploader.cpython-38-darwin.so
PyCUploader-1.0.2.dist-info/METADATA
PyCUploader-1.0.2.dist-info/WHEEL
PyCUploader-1.0.2.dist-info/top_level.txt
PyCUploader-1.0.2.dist-info/RECORD
